yulin_mssql_mcp/__init__.py
yulin_mssql_mcp/__main__.py
yulin_mssql_mcp/server.py
yulin_mssql_mcp-0.1.2.dist-info/METADATA
yulin_mssql_mcp-0.1.2.dist-info/WHEEL
yulin_mssql_mcp-0.1.2.dist-info/entry_points.txt
yulin_mssql_mcp-0.1.2.dist-info/licenses/LICENSE
yulin_mssql_mcp-0.1.2.dist-info/RECORD
