Metadata-Version: 2.4
Name: yulin-mssql-mcp
Version: 0.1.2
Summary: A Model Context Protocol (MCP) server that enables secure interaction with Microsoft SQL Server databases.
Author-email: yulin0629 <yulin0629@gmail.com>
License: MIT
License-File: LICENSE
Keywords: ai,database,mcp,mssql,sql-server
Classifier: Development Status :: 4 - Beta
Classifier: Intended Audience :: Developers
Classifier: License :: OSI Approved :: MIT License
Classifier: Programming Language :: Python :: 3
Classifier: Programming Language :: Python :: 3.11
Classifier: Programming Language :: Python :: 3.12
Requires-Python: >=3.11
Requires-Dist: mcp>=1.0.0
Requires-Dist: pymssql>=2.2.8
